pyxcpcanmaster-0.0.2.dist-info/licenses/LICENSE
xcp_can_master/__init__.py
xcp_can_master/xcp_master.py
pyxcpcanmaster-0.0.2.dist-info/METADATA
pyxcpcanmaster-0.0.2.dist-info/WHEEL
pyxcpcanmaster-0.0.2.dist-info/top_level.txt
pyxcpcanmaster-0.0.2.dist-info/RECORD
