Metadata-Version: 2.4
Name: PyXcpCanMaster
Version: 0.0.2
Summary: Parse ASAP2 A2L file
Home-page: https://github.com/sgnes/XcpCanMaster
Author: Sgnes
Author-email: sgnes0514@gmai.com
Classifier: Programming Language :: Python :: 3
Classifier: License :: OSI Approved :: MIT License
Classifier: Operating System :: OS Independent
Requires-Python: >=3.8
License-File: LICENSE
Requires-Dist: python-can
Requires-Dist: loguru
Dynamic: author
Dynamic: author-email
Dynamic: classifier
Dynamic: description
Dynamic: description-content-type
Dynamic: home-page
Dynamic: license-file
Dynamic: requires-dist
Dynamic: requires-python
Dynamic: summary
